CHP/CHP.py
CHP/TEXT.py
CHP/__init__.py
CHP_Editor-1.0.2.dist-info/METADATA
CHP_Editor-1.0.2.dist-info/WHEEL
CHP_Editor-1.0.2.dist-info/top_level.txt
CHP_Editor-1.0.2.dist-info/RECORD
