Metadata-Version: 2.1
Name: CHP-Editor
Version: 1.0.2
Summary: Classroom Assistant
Home-page: UNKNOWN
Author: ArMafer
Author-email: <angelshaparro@outlook.com>
License: UNKNOWN
Keywords: python,classroom,homework,music player,calculator,wikipedia
Platform: UNKNOWN
Classifier: Development Status :: 1 - Planning
Classifier: Intended Audience :: Developers
Classifier: Programming Language :: Python :: 3
Classifier: Operating System :: Microsoft :: Windows
Requires-Dist: opencv-python
Requires-Dist: pyautogui
